gdf2bokeh/__init__.py
gdf2bokeh/app_map.py
gdf2bokeh/geometry.py
gdf2bokeh/global_values.py
gdf2bokeh/layer.py
gdf2bokeh/main.py
gdf2bokeh/models.py
gdf2bokeh-3.3.0.dist-info/LICENSE
gdf2bokeh-3.3.0.dist-info/WHEEL
gdf2bokeh-3.3.0.dist-info/METADATA
gdf2bokeh-3.3.0.dist-info/RECORD
