Metadata-Version: 2.1
Name: gdf2bokeh
Version: 3.3.0
Summary: An easy way to map geodataframes on bokeh
License: GPL3
Author: amauryval
Author-email: amauryval@gmail.com
Requires-Python: >=3.13,<4.0
Classifier: License :: Other/Proprietary License
Classifier: Programming Language :: Python :: 3
Requires-Dist: bokeh (>=3.6.2,<4.0.0)
Requires-Dist: geopandas (>=1.0.1,<2.0.0)
